{
  "projects": [
    {
      "title": "Fixa koetboeallar",
      "color": "#000000",
      "id": 3
    },
    {
      "title": "Koepa salsa till salzcicoa och springa på stan",
      "color": "#000000",
      "id": 4
    }
  ],
  "tasks": [
    {
      "projectId": 3,
      "title": "Flicker n noise",
      "id": 5
    },
    {
      "projectId": 4,
      "title": "pussap ussa saaaaaaaara",
      "id": 6
    }
  ],
  "timelogs": [
    {
      "projectId": 3,
      "taskTitle": "Flicker n noise",
      "startDate": "Oct-26-2022",
      "startTime": "13:26:01",
      "endDate": "",
      "endTime": "",
      "totalTimeInSeconds": 4,
      "id": 6
    },
    {
      "projectId": 4,
      "taskTitle": "pussap ussa saaaaaaaara",
      "startDate": "Oct-27-2022",
      "startTime": "07:40:47",
      "endDate": "",
      "endTime": "",
      "totalTimeInSeconds": 6,
      "id": 9
    }
  ]
}